{
  "ID": "2ae06fa4-3ce8-4edc-b2dc-38ac074c091c",
  "Version": "2.3.3.0",
  "Name": "user_window",
  "Content": {
    "Content": {
      "Animation": {
        "Duration": 0,
        "Speed": 1.0,
        "Timelines": [],
        "ctype": "TimelineActionData"
      },
      "AnimationList": [],
      "ObjectData": {
        "Tag": 21,
        "Children": [
          {
            "FileData": {
              "Type": "Normal",
              "Path": "img_bg_user.png",
              "Plist": ""
            },
            "BlendFunc": {
              "Src": 770,
              "Dst": 771
            },
            "AnchorPoint": {
              "ScaleX": 0.5,
              "ScaleY": 0.5
            },
            "Position": {
              "X": 320.0,
              "Y": 240.0
            },
            "Scale": {
              "ScaleX": 1.0,
              "ScaleY": 1.0
            },
            "CColor": {},
            "IconVisible": false,
            "PrePosition": {
              "X": 0.5,
              "Y": 0.4528
            },
            "PreSize": {
              "X": 0.6141,
              "Y": 0.8302
            },
            "LeftMargin": 123.5,
            "RightMargin": 123.5,
            "TopMargin": 70.0,
            "BottomMargin": 20.0,
            "Tag": 22,
            "ActionTag": -1512483959,
            "Size": {
              "X": 393.0,
              "Y": 440.0
            },
            "Name": "img_bg_user",
            "ctype": "SpriteObjectData"
          },
          {
            "CheckedState": true,
            "NormalBackFileData": {
              "Type": "Normal",
              "Path": "ck_sex_normal.png",
              "Plist": ""
            },
            "PressedBackFileData": {
              "Type": "Normal",
              "Path": "ck_sex_focus.png",
              "Plist": ""
            },
            "DisableBackFileData": {
              "Type": "Normal",
              "Path": "ck_sex_normal.png",
              "Plist": ""
            },
            "NodeNormalFileData": {
              "Type": "Normal",
              "Path": "ck_sex_checked.png",
              "Plist": ""
            },
            "NodeDisableFileData": {
              "Type": "Normal",
              "Path": "ck_sex_checked.png",
              "Plist": ""
            },
            "TouchEnable": true,
            "AnchorPoint": {
              "ScaleX": 0.5,
              "ScaleY": 0.5
            },
            "Position": {
              "X": 327.0,
              "Y": 273.0
            },
            "Scale": {
              "ScaleX": 1.0,
              "ScaleY": 1.0
            },
            "CColor": {},
            "IconVisible": false,
            "PrePosition": {
              "X": 0.5109,
              "Y": 0.5151
            },
            "PreSize": {
              "X": 0.0313,
              "Y": 0.0547
            },
            "LeftMargin": 317.0,
            "RightMargin": 303.0,
            "TopMargin": 242.5,
            "BottomMargin": 258.5,
            "Tag": 23,
            "ActionTag": -97556886,
            "Size": {
              "X": 20.0,
              "Y": 29.0
            },
            "Name": "ck_male",
            "ctype": "CheckBoxObjectData"
          },
          {
            "CheckedState": true,
            "NormalBackFileData": {
              "Type": "Normal",
              "Path": "ck_sex_normal.png",
              "Plist": ""
            },
            "PressedBackFileData": {
              "Type": "Normal",
              "Path": "ck_sex_focus.png",
              "Plist": ""
            },
            "DisableBackFileData": {
              "Type": "Normal",
              "Path": "ck_sex_normal.png",
              "Plist": ""
            },
            "NodeNormalFileData": {
              "Type": "Normal",
              "Path": "ck_sex_checked.png",
              "Plist": ""
            },
            "NodeDisableFileData": {
              "Type": "Normal",
              "Path": "ck_sex_checked.png",
              "Plist": ""
            },
            "TouchEnable": true,
            "AnchorPoint": {
              "ScaleX": 0.5,
              "ScaleY": 0.5
            },
            "Position": {
              "X": 430.0,
              "Y": 273.0
            },
            "Scale": {
              "ScaleX": 1.0,
              "ScaleY": 1.0
            },
            "CColor": {},
            "IconVisible": false,
            "PrePosition": {
              "X": 0.6719,
              "Y": 0.5151
            },
            "PreSize": {
              "X": 0.0313,
              "Y": 0.0547
            },
            "LeftMargin": 420.0,
            "RightMargin": 200.0,
            "TopMargin": 242.5,
            "BottomMargin": 258.5,
            "Tag": 24,
            "ActionTag": -148804827,
            "Size": {
              "X": 20.0,
              "Y": 29.0
            },
            "Name": "ck_female",
            "ctype": "CheckBoxObjectData"
          },
          {
            "FileData": {
              "Type": "Default",
              "Path": "Default/ImageFile.png",
              "Plist": ""
            },
            "Scale9Width": 46,
            "Scale9Height": 46,
            "AnchorPoint": {
              "ScaleX": 0.5,
              "ScaleY": 0.5
            },
            "Position": {
              "X": 174.0,
              "Y": 357.0
            },
            "Scale": {
              "ScaleX": 1.0,
              "ScaleY": 1.0
            },
            "CColor": {},
            "IconVisible": false,
            "PrePosition": {
              "X": 0.2719,
              "Y": 0.6736
            },
            "PreSize": {
              "X": 0.0656,
              "Y": 0.1094
            },
            "LeftMargin": 153.0,
            "RightMargin": 445.0,
            "TopMargin": 144.0,
            "BottomMargin": 328.0,
            "Tag": 25,
            "ActionTag": -2080845975,
            "Size": {
              "X": 42.0,
              "Y": 58.0
            },
            "Name": "img_head",
            "ctype": "ImageViewObjectData"
          },
          {
            "FileData": {
              "Type": "Normal",
              "Path": "img_head_border.png",
              "Plist": ""
            },
            "BlendFunc": {
              "Src": 770,
              "Dst": 771
            },
            "AnchorPoint": {
              "ScaleX": 0.5,
              "ScaleY": 0.5
            },
            "Position": {
              "X": 173.0,
              "Y": 355.0
            },
            "Scale": {
              "ScaleX": 1.0,
              "ScaleY": 1.0
            },
            "CColor": {},
            "IconVisible": false,
            "PrePosition": {
              "X": 0.2703,
              "Y": 0.6698
            },
            "PreSize": {
              "X": 0.0688,
              "Y": 0.1302
            },
            "LeftMargin": 151.0,
            "RightMargin": 445.0,
            "TopMargin": 140.5,
            "BottomMargin": 320.5,
            "Tag": 26,
            "ActionTag": -2094153870,
            "Size": {
              "X": 44.0,
              "Y": 69.0
            },
            "Name": "img_head_border",
            "ctype": "SpriteObjectData"
          },
          {
            "FontSize": 14,
            "ButtonText": "Button",
            "TextColor": {
              "R": 65,
              "G": 65,
              "B": 70
            },
            "DisabledFileData": {
              "Type": "Normal",
              "Path": "btn_head_z.png",
              "Plist": ""
            },
            "PressedFileData": {
              "Type": "Normal",
              "Path": "btn_head_a.png",
              "Plist": ""
            },
            "NormalFileData": {
              "Type": "Normal",
              "Path": "btn_head_z.png",
              "Plist": ""
            },
            "Scale9Enable": true,
            "Scale9OriginX": 15,
            "Scale9OriginY": 10,
            "Scale9Width": 28,
            "Scale9Height": 12,
            "OutlineColor": {
              "G": 0,
              "B": 0
            },
            "ShadowColor": {
              "R": 110,
              "G": 110,
              "B": 110
            },
            "ShadowOffsetX": 2.0,
            "ShadowOffsetY": -2.0,
            "TouchEnable": true,
            "AnchorPoint": {
              "ScaleX": 0.5,
              "ScaleY": 0.5
            },
            "Position": {
              "X": 232.0,
              "Y": 373.0
            },
            "Scale": {
              "ScaleX": 1.0,
              "ScaleY": 1.0
            },
            "CColor": {},
            "IconVisible": false,
            "PrePosition": {
              "X": 0.3625,
              "Y": 0.7038
            },
            "PreSize": {
              "X": 0.0906,
              "Y": 0.0604
            },
            "LeftMargin": 203.0,
            "RightMargin": 379.0,
            "TopMargin": 141.0,
            "BottomMargin": 357.0,
            "Tag": 27,
            "ActionTag": -374994630,
            "Size": {
              "X": 58.0,
              "Y": 32.0
            },
            "Name": "btn_head",
            "ctype": "ButtonObjectData"
          },
          {
            "LabelText": "",
            "LabelBMFontFile_CNB": {
              "Type": "Default",
              "Path": "Default/defaultBMFont.fnt",
              "Plist": ""
            },
            "AnchorPoint": {
              "ScaleX": 0.5,
              "ScaleY": 0.5
            },
            "Position": {
              "X": 295.0,
              "Y": 361.0
            },
            "Scale": {
              "ScaleX": 1.0,
              "ScaleY": 1.0
            },
            "CColor": {},
            "IconVisible": false,
            "PrePosition": {
              "X": 0.4609,
              "Y": 0.6811
            },
            "PreSize": {
              "X": 0.0,
              "Y": 0.0
            },
            "LeftMargin": 295.0,
            "RightMargin": 345.0,
            "TopMargin": 169.0,
            "BottomMargin": 361.0,
            "UserData": "com_id_gold_fnt",
            "Tag": 28,
            "ActionTag": 502167908,
            "Size": {
              "X": 0.0,
              "Y": 0.0
            },
            "Name": "bf_name",
            "ctype": "TextBMFontObjectData"
          },
          {
            "FileData": {
              "Type": "Default",
              "Path": "Default/ImageFile.png",
              "Plist": ""
            },
            "Scale9Width": 46,
            "Scale9Height": 46,
            "AnchorPoint": {
              "ScaleX": 0.5,
              "ScaleY": 0.5
            },
            "Position": {
              "X": 284.0,
              "Y": 339.0
            },
            "Scale": {
              "ScaleX": 1.0,
              "ScaleY": 1.0
            },
            "CColor": {},
            "IconVisible": false,
            "PrePosition": {
              "X": 0.4437,
              "Y": 0.6396
            },
            "PreSize": {
              "X": 0.0984,
              "Y": 0.0377
            },
            "LeftMargin": 252.5,
            "RightMargin": 324.5,
            "TopMargin": 181.0,
            "BottomMargin": 329.0,
            "Tag": 29,
            "ActionTag": 1279461499,
            "Size": {
              "X": 63.0,
              "Y": 20.0
            },
            "Name": "img_title",
            "ctype": "ImageViewObjectData"
          },
          {
            "LabelText": "",
            "LabelBMFontFile_CNB": {
              "Type": "Default",
              "Path": "Default/defaultBMFont.fnt",
              "Plist": ""
            },
            "AnchorPoint": {
              "ScaleX": 0.5,
              "ScaleY": 0.5
            },
            "Position": {
              "X": 395.0,
              "Y": 326.0
            },
            "Scale": {
              "ScaleX": 1.0,
              "ScaleY": 1.0
            },
            "CColor": {},
            "IconVisible": false,
            "PrePosition": {
              "X": 0.6172,
              "Y": 0.6151
            },
            "PreSize": {
              "X": 0.0,
              "Y": 0.0
            },
            "LeftMargin": 395.0,
            "RightMargin": 245.0,
            "TopMargin": 204.0,
            "BottomMargin": 326.0,
            "UserData": "big_gold_num_fnt",
            "Tag": 30,
            "ActionTag": 2040905746,
            "Size": {
              "X": 0.0,
              "Y": 0.0
            },
            "Name": "bf_level",
            "ctype": "TextBMFontObjectData"
          },
          {
            "LabelText": "",
            "LabelBMFontFile_CNB": {
              "Type": "Default",
              "Path": "Default/defaultBMFont.fnt",
              "Plist": ""
            },
            "AnchorPoint": {
              "ScaleX": 0.5,
              "ScaleY": 0.5
            },
            "Position": {
              "X": 270.0,
              "Y": 175.0
            },
            "Scale": {
              "ScaleX": 1.0,
              "ScaleY": 1.0
            },
            "CColor": {},
            "IconVisible": false,
            "PrePosition": {
              "X": 0.4219,
              "Y": 0.3302
            },
            "PreSize": {
              "X": 0.0,
              "Y": 0.0
            },
            "LeftMargin": 270.0,
            "RightMargin": 370.0,
            "TopMargin": 355.0,
            "BottomMargin": 175.0,
            "UserData": "big_gold_num_fnt",
            "Tag": 31,
            "ActionTag": -739480602,
            "Size": {
              "X": 0.0,
              "Y": 0.0
            },
            "Name": "bf_ticket",
            "ctype": "TextBMFontObjectData"
          },
          {
            "LabelText": "",
            "LabelBMFontFile_CNB": {
              "Type": "Default",
              "Path": "Default/defaultBMFont.fnt",
              "Plist": ""
            },
            "AnchorPoint": {
              "ScaleX": 0.5,
              "ScaleY": 0.5
            },
            "Position": {
              "X": 252.0,
              "Y": 129.0
            },
            "Scale": {
              "ScaleX": 1.0,
              "ScaleY": 1.0
            },
            "CColor": {},
            "IconVisible": false,
            "PrePosition": {
              "X": 0.3938,
              "Y": 0.2434
            },
            "PreSize": {
              "X": 0.0,
              "Y": 0.0
            },
            "LeftMargin": 252.0,
            "RightMargin": 388.0,
            "TopMargin": 401.0,
            "BottomMargin": 129.0,
            "UserData": "big_gold_num_fnt",
            "Tag": 32,
            "ActionTag": -1189465642,
            "Size": {
              "X": 0.0,
              "Y": 0.0
            },
            "Name": "bf_gold",
            "ctype": "TextBMFontObjectData"
          },
          {
            "LabelText": "",
            "LabelBMFontFile_CNB": {
              "Type": "Default",
              "Path": "Default/defaultBMFont.fnt",
              "Plist": ""
            },
            "AnchorPoint": {
              "ScaleX": 0.5,
              "ScaleY": 0.5
            },
            "Position": {
              "X": 252.0,
              "Y": 83.0
            },
            "Scale": {
              "ScaleX": 1.0,
              "ScaleY": 1.0
            },
            "CColor": {},
            "IconVisible": false,
            "PrePosition": {
              "X": 0.3938,
              "Y": 0.1566
            },
            "PreSize": {
              "X": 0.0,
              "Y": 0.0
            },
            "LeftMargin": 252.0,
            "RightMargin": 388.0,
            "TopMargin": 447.0,
            "BottomMargin": 83.0,
            "UserData": "big_gold_num_fnt",
            "Tag": 33,
            "ActionTag": -247857914,
            "Size": {
              "X": 0.0,
              "Y": 0.0
            },
            "Name": "bf_continuous_win",
            "ctype": "TextBMFontObjectData"
          },
          {
            "LabelText": "",
            "LabelBMFontFile_CNB": {
              "Type": "Default",
              "Path": "Default/defaultBMFont.fnt",
              "Plist": ""
            },
            "AnchorPoint": {
              "ScaleX": 0.5,
              "ScaleY": 0.5
            },
            "Position": {
              "X": 395.0,
              "Y": 129.0
            },
            "Scale": {
              "ScaleX": 1.0,
              "ScaleY": 1.0
            },
            "CColor": {},
            "IconVisible": false,
            "PrePosition": {
              "X": 0.6172,
              "Y": 0.2434
            },
            "PreSize": {
              "X": 0.0,
              "Y": 0.0
            },
            "LeftMargin": 395.0,
            "RightMargin": 245.0,
            "TopMargin": 401.0,
            "BottomMargin": 129.0,
            "UserData": "big_gold_num_fnt",
            "Tag": 34,
            "ActionTag": 271710555,
            "Size": {
              "X": 0.0,
              "Y": 0.0
            },
            "Name": "bf_total_game",
            "ctype": "TextBMFontObjectData"
          },
          {
            "LabelText": "",
            "LabelBMFontFile_CNB": {
              "Type": "Default",
              "Path": "Default/defaultBMFont.fnt",
              "Plist": ""
            },
            "AnchorPoint": {
              "ScaleX": 0.5,
              "ScaleY": 0.5
            },
            "Position": {
              "X": 377.0,
              "Y": 84.0
            },
            "Scale": {
              "ScaleX": 1.0,
              "ScaleY": 1.0
            },
            "CColor": {},
            "IconVisible": false,
            "PrePosition": {
              "X": 0.5891,
              "Y": 0.1585
            },
            "PreSize": {
              "X": 0.0,
              "Y": 0.0
            },
            "LeftMargin": 377.0,
            "RightMargin": 263.0,
            "TopMargin": 446.0,
            "BottomMargin": 84.0,
            "UserData": "big_gold_num_fnt",
            "Tag": 35,
            "ActionTag": -1356401029,
            "Size": {
              "X": 0.0,
              "Y": 0.0
            },
            "Name": "bf_win_rate",
            "ctype": "TextBMFontObjectData"
          },
          {
            "FontSize": 14,
            "ButtonText": "Button",
            "TextColor": {
              "R": 65,
              "G": 65,
              "B": 70
            },
            "DisabledFileData": {
              "Type": "Normal",
              "Path": "btn_close_z.png",
              "Plist": ""
            },
            "PressedFileData": {
              "Type": "Normal",
              "Path": "btn_close_a.png",
              "Plist": ""
            },
            "NormalFileData": {
              "Type": "Normal",
              "Path": "btn_close_z.png",
              "Plist": ""
            },
            "Scale9Enable": true,
            "Scale9OriginX": 15,
            "Scale9OriginY": 11,
            "Scale9Width": 17,
            "Scale9Height": 47,
            "OutlineColor": {
              "G": 0,
              "B": 0
            },
            "ShadowColor": {
              "R": 110,
              "G": 110,
              "B": 110
            },
            "ShadowOffsetX": 2.0,
            "ShadowOffsetY": -2.0,
            "TouchEnable": true,
            "AnchorPoint": {
              "ScaleX": 0.5,
              "ScaleY": 0.5
            },
            "Position": {
              "X": 499.0,
              "Y": 410.0
            },
            "Scale": {
              "ScaleX": 1.0,
              "ScaleY": 1.0
            },
            "CColor": {},
            "IconVisible": false,
            "PrePosition": {
              "X": 0.7797,
              "Y": 0.7736
            },
            "PreSize": {
              "X": 0.0734,
              "Y": 0.1302
            },
            "LeftMargin": 475.5,
            "RightMargin": 117.5,
            "TopMargin": 85.5,
            "BottomMargin": 375.5,
            "Tag": 19,
            "ActionTag": -813488933,
            "Size": {
              "X": 47.0,
              "Y": 69.0
            },
            "Name": "btn_close",
            "ctype": "ButtonObjectData"
          },
          {
            "FileData": {
              "Type": "Normal",
              "Path": "user_head_window.json",
              "Plist": ""
            },
            "StretchWidthEnable": false,
            "StretchHeightEnable": false,
            "InnerActionSpeed": 1.0,
            "AnchorPoint": {},
            "Position": {
              "X": 0.0,
              "Y": 0.0
            },
            "Scale": {
              "ScaleX": 1.0,
              "ScaleY": 1.0
            },
            "CColor": {},
            "IconVisible": true,
            "PrePosition": {
              "X": 0.0,
              "Y": 0.0
            },
            "PreSize": {
              "X": 1.0,
              "Y": 1.0
            },
            "Tag": 38,
            "ActionTag": -1250877304,
            "Size": {
              "X": 640.0,
              "Y": 530.0
            },
            "Name": "layer_user_head",
            "ctype": "ProjectNodeObjectData"
          }
        ],
        "Size": {
          "X": 640.0,
          "Y": 530.0
        },
        "Name": "Scene",
        "ctype": "SingleNodeObjectData"
      },
      "UsedResources": [
        "btn_close_a.png",
        "btn_close_z.png",
        "btn_head_a.png",
        "btn_head_z.png",
        "ck_sex_checked.png",
        "ck_sex_focus.png",
        "ck_sex_normal.png",
        "Default/defaultBMFont.fnt",
        "Default/defaultBMFont.png",
        "Default/ImageFile.png",
        "img_bg_user.png",
        "img_head_border.png",
        "user_head_window.json"
      ],
      "ctype": "GameFileData"
    }
  },
  "Type": "Scene"
}